operetta_compose/__FRACTAL_MANIFEST__.json
operetta_compose/__init__.py
operetta_compose/utils.py
operetta_compose/io/__init__.py
operetta_compose/tasks/__init__.py
operetta_compose/tasks/condition_registration.py
operetta_compose/tasks/feature_classification.py
operetta_compose/tasks/harmony_to_ome_zarr.py
operetta_compose/tasks/regionprops_measurement.py
operetta_compose/tasks/stardist_segmentation.py
operetta_compose-0.2.13.dist-info/licenses/LICENSE
operetta_compose-0.2.13.dist-info/METADATA
operetta_compose-0.2.13.dist-info/WHEEL
operetta_compose-0.2.13.dist-info/top_level.txt
operetta_compose-0.2.13.dist-info/RECORD
