Metadata-Version: 2.4
Name: operetta-compose
Version: 0.2.13
Summary: Fractal tasks for the Opera/Operetta microscope and drug response profiling
Author-email: Fabio Steffen <fabio.steffen@uzh.ch>
License: BSD-3-Clause
Project-URL: Documentation, https://leukemia-kispi.github.io/operetta-compose/
Project-URL: Repository, https://github.com/leukemia-kispi/operetta-compose.git
Project-URL: Issues, https://github.com/leukemia-kispi/operetta-compose/issues
Requires-Python: >=3.10
License-File: LICENSE
Requires-Dist: fractal-tasks-core
Requires-Dist: ome-zarr
Requires-Dist: imagecodecs
Requires-Dist: tqdm
Requires-Dist: xmltodict
Requires-Dist: pydantic
Requires-Dist: csbdeep
Requires-Dist: stardist
Requires-Dist: numpy<2
Requires-Dist: tensorflow
Requires-Dist: tensorflow-metal; platform_system == "Darwin"
Requires-Dist: napari-feature-classifier>=0.3.0
Requires-Dist: ngio==0.1.6
Provides-Extra: dev
Requires-Dist: devtools; extra == "dev"
Requires-Dist: pytest; extra == "dev"
Requires-Dist: requests; extra == "dev"
Requires-Dist: build; extra == "dev"
Requires-Dist: jsonschema; extra == "dev"
Requires-Dist: bumpver; extra == "dev"
Requires-Dist: pre-commit; extra == "dev"
Requires-Dist: pytest-cov; extra == "dev"
Requires-Dist: pytest-dependency; extra == "dev"
Dynamic: license-file
